dagster_contrib_gcp/__init__.py
dagster_contrib_gcp/cloud_run/__init__.py
dagster_contrib_gcp/cloud_run/run_launcher.py
dagster_contrib_gcp-0.0.9.dist-info/METADATA
dagster_contrib_gcp-0.0.9.dist-info/WHEEL
dagster_contrib_gcp-0.0.9.dist-info/top_level.txt
dagster_contrib_gcp-0.0.9.dist-info/RECORD
