Metadata-Version: 2.4
Name: dagster-contrib-gcp
Version: 0.0.9
Summary: Community contributed Google Cloud Platform integration
Requires-Python: >=3.10
Requires-Dist: dagster>=1.9.0
Requires-Dist: google-cloud-run>=0.10.10
Requires-Dist: google-cloud-secret-manager>=2.23.1
Requires-Dist: tenacity>=8.0.0
